tests/__init__.py
tests/test_xpath_identifier.py
tests/fixtures/__init__.py
tests/fixtures/test_email.eml
tests/fixtures/test_html.html
xpath_identifier/__init__.py
xpath_identifier/main.py
xpath_identifier-0.0.9.dist-info/LICENSE
xpath_identifier-0.0.9.dist-info/METADATA
xpath_identifier-0.0.9.dist-info/WHEEL
xpath_identifier-0.0.9.dist-info/top_level.txt
xpath_identifier-0.0.9.dist-info/RECORD
