Metadata-Version: 2.1
Name: xpath-identifier
Version: 0.0.9
Summary: Identify Xpath expressions in a given document
Home-page: https://github.com/devtanna/xpath-identifier
Author-email: Dev Tanna <dev.tanna@gmail.com>
Project-URL: Homepage, https://github.com/devtanna/xpath-identifier
Project-URL: Bug Tracker, https://github.com/devtanna/xpath-identifier/issues
Keywords: xpath,identifier,parser
Classifier: Programming Language :: Python :: 3
Classifier: License :: OSI Approved :: MIT License
Classifier: Operating System :: OS Independent
Requires-Python: >=3.7
License-File: LICENSE
Requires-Dist: beautifulsoup4 (==4.11.1)
Requires-Dist: lxml (==4.9.1)
Requires-Dist: regex (==2022.10.31)
